CHANGES.txt
MANIFEST.in
README.txt
RELEASE.txt
doc.txt
setup.cfg
setup.py
roadrunner/__init__.py
roadrunner/integration.txt
roadrunner/recipe.py
roadrunner/recipe.txt
roadrunner/runner.py
roadrunner/testrunner.py
roadrunner/tests.py
roadrunner.egg-info/PKG-INFO
roadrunner.egg-info/SOURCES.txt
roadrunner.egg-info/dependency_links.txt
roadrunner.egg-info/entry_points.txt
roadrunner.egg-info/not-zip-safe
roadrunner.egg-info/requires.txt
roadrunner.egg-info/top_level.txt
roadrunner/platform/__init__.py
roadrunner/platform/osx.py