Metadata-Version: 1.0
Name: roadrunner
Version: 0.2.3.1
Summary: testrunner for test-driven development
Home-page: UNKNOWN
Author: Jordan Baker
Author-email: jbb@scryent.com
License: ZPL
Keywords: zope buildout TDD testing
Platform: UNKNOWN
